{"trial_id": "739f4f885ea9b592a1bac47f06fc3d27", "hyperparameters": {"space": [{"class_name": "Choice", "config": {"name": "af_LSTM", "default": "relu", "conditions": [], "values": ["relu", "sigmoid", "tanh", "softmax", "softsign", "selu", "elu"], "ordered": false}}, {"class_name": "Choice", "config": {"name": "raf_LSTM", "default": "sigmoid", "conditions": [], "values": ["sigmoid"], "ordered": false}}, {"class_name": "Choice", "config": {"name": "af_dense", "default": "sigmoid", "conditions": [], "values": ["sigmoid"], "ordered": false}}, {"class_name": "Choice", "config": {"name": "optimizer", "default": "adam", "conditions": [], "values": ["adam", "sgd"], "ordered": false}}, {"class_name": "Choice", "config": {"name": "learning_rate", "default": 0.01, "conditions": [], "values": [0.01, 0.001, 0.0001], "ordered": true}}, {"class_name": "Choice", "config": {"name": "thresholds_BA", "default": 0.5, "conditions": [], "values": [0.5, 0.51, 0.6, 0.7], "ordered": true}}], "values": {"af_LSTM": "sigmoid", "raf_LSTM": "sigmoid", "af_dense": "sigmoid", "optimizer": "adam", "learning_rate": 0.0001, "thresholds_BA": 0.51, "tuner/epochs": 8, "tuner/initial_epoch": 3, "tuner/bracket": 1, "tuner/round": 1, "tuner/trial_id": "16f3c0d31fad7378dd9b4be421a3e1a9"}}, "metrics": {"metrics": {"loss": {"direction": "min", "observations": [{"value": [0.689934253692627], "step": 0}]}, "binary_accuracy": {"direction": "max", "observations": [{"value": [0.5213596224784851], "step": 0}]}, "val_loss": {"direction": "min", "observations": [{"value": [0.6893419623374939], "step": 0}]}, "val_binary_accuracy": {"direction": "max", "observations": [{"value": [0.5219861268997192], "step": 0}]}}}, "score": 0.5219861268997192, "best_step": 0, "status": "COMPLETED"}