{"trial_id": "b05c4e51b413626d05c195b811b7d39a", "hyperparameters": {"space": [{"class_name": "Choice", "config": {"name": "af_LSTM", "default": "relu", "conditions": [], "values": ["relu", "sigmoid", "tanh", "softmax", "softsign", "selu", "elu"], "ordered": false}}, {"class_name": "Choice", "config": {"name": "raf_LSTM", "default": "sigmoid", "conditions": [], "values": ["sigmoid"], "ordered": false}}, {"class_name": "Choice", "config": {"name": "af_dense", "default": "sigmoid", "conditions": [], "values": ["sigmoid"], "ordered": false}}, {"class_name": "Choice", "config": {"name": "optimizer", "default": "adam", "conditions": [], "values": ["adam", "sgd"], "ordered": false}}, {"class_name": "Choice", "config": {"name": "learning_rate", "default": 0.01, "conditions": [], "values": [0.01, 0.001, 0.0001], "ordered": true}}, {"class_name": "Choice", "config": {"name": "thresholds_BA", "default": 0.5, "conditions": [], "values": [0.5, 0.51, 0.6, 0.7], "ordered": true}}], "values": {"af_LSTM": "tanh", "raf_LSTM": "sigmoid", "af_dense": "sigmoid", "optimizer": "sgd", "learning_rate": 0.001, "thresholds_BA": 0.7, "tuner/epochs": 3, "tuner/initial_epoch": 0, "tuner/bracket": 1, "tuner/round": 0}}, "metrics": {"metrics": {"loss": {"direction": "min", "observations": [{"value": [0.2484675794839859], "step": 0}]}, "binary_accuracy": {"direction": "max", "observations": [{"value": [0.47491908073425293], "step": 0}]}, "val_loss": {"direction": "min", "observations": [{"value": [0.24818859994411469], "step": 0}]}, "val_binary_accuracy": {"direction": "max", "observations": [{"value": [0.47765377163887024], "step": 0}]}}}, "score": 0.47765377163887024, "best_step": 0, "status": "COMPLETED"}